floa/__init__.py
floa/node.py
floa/output.py
floa-0.0.1.dist-info/LICENSE
floa-0.0.1.dist-info/METADATA
floa-0.0.1.dist-info/WHEEL
floa-0.0.1.dist-info/top_level.txt
floa-0.0.1.dist-info/RECORD
