Metadata-Version: 2.2
Name: floa
Version: 0.0.1
Summary: Quick building AI workflow.
Home-page: https://github.com/NNNINNN/FLOA
Author: NNNINNN
Author-email: jianningwork@outlook.com
Classifier: Programming Language :: Python :: 3
Classifier: License :: OSI Approved :: MIT License
Classifier: Operating System :: OS Independent
Requires-Python: >=3.6
License-File: LICENSE
Dynamic: author
Dynamic: author-email
Dynamic: classifier
Dynamic: description
Dynamic: description-content-type
Dynamic: home-page
Dynamic: requires-python
Dynamic: summary
